[{"years_pro": 3, "status": "ACT", "first_name": "Rodney", "last_name": "McLeod", "gsis_id": "00-0028899", "weight": 195, "position": "FS", "playerid": "00-0028899", "profile_id": 2534832, "number": 23, "uniform_number": 23, "height": 70, "esb_id": "MCL709174", "college": "Virginia", "birthdate": "6/23/1990", "full_name": "Rodney McLeod", "team": "STL", "player_id": "00-0028899", "gsis_name": "R.McLeod", "profile_url": "http://www.nfl.com/player/rodneymcleod/2534832/profile", "name": "Rodney McLeod"}, {"years_pro": 5, "status": "ACT", "first_name": "Alex", "last_name": "Carrington", "gsis_id": "00-0027677", "weight": 301, "position": "DE", "playerid": "00-0027677", "profile_id": 496766, "number": 92, "uniform_number": 92, "height": 77, "esb_id": "CAR486635", "college": "Arkansas State", "birthdate": "6/19/1987", "full_name": "Alex Carrington", "team": "STL", "player_id": "00-0027677", "gsis_name": "A.Carrington", "profile_url": "http://www.nfl.com/player/alexcarrington/496766/profile", "name": "Alex Carrington"}, {"years_pro": 3, "status": "ACT", "first_name": "Johnny", "last_name": "Hekker", "gsis_id": "00-0028872", "weight": 236, "position": "P", "playerid": "00-0028872", "profile_id": 2535663, "number": 6, "uniform_number": 6, "height": 77, "esb_id": "HEK403291", "college": "Oregon State", "birthdate": "2/8/1990", "full_name": "Johnny Hekker", "team": "STL", "player_id": "00-0028872", "gsis_name": "J.Hekker", "profile_url": "http://www.nfl.com/player/johnnyhekker/2535663/profile", "name": "Johnny Hekker"}, {"years_pro": 3, "status": "ACT", "first_name": "Matt", "last_name": "Conrath", "gsis_id": "00-0028878", "weight": 306, "position": "DT", "playerid": "00-0028878", "profile_id": 2534836, "number": 71, "uniform_number": 71, "height": 79, "esb_id": "CON677425", "college": "Virginia", "birthdate": "8/11/1989", "full_name": "Matt Conrath", "team": "STL", "player_id": "00-0028878", "gsis_name": "M.Conrath", "profile_url": "http://www.nfl.com/player/mattconrath/2534836/profile", "name": "Matt Conrath"}, {"years_pro": 9, "status": "ACT", "first_name": "Davin", "last_name": "Joseph", "gsis_id": "00-0024238", "weight": 313, "position": "G", "playerid": "00-0024238", "profile_id": 2495871, "number": 69, "uniform_number": 69, "height": 75, "esb_id": "JOS174977", "college": "Oklahoma", "birthdate": "11/22/1983", "full_name": "Davin Joseph", "team": "STL", "player_id": "00-0024238", "gsis_name": "D.Joseph", "profile_url": "http://www.nfl.com/player/davinjoseph/2495871/profile", "name": "Davin Joseph"}, {"years_pro": 4, "status": "ACT", "first_name": "Lance", "last_name": "Kendricks", "gsis_id": "00-0027985", "weight": 250, "position": "TE", "playerid": "00-0027985", "profile_id": 2495187, "number": 88, "uniform_number": 88, "height": 75, "esb_id": "KEN102780", "college": "Wisconsin", "birthdate": "1/30/1988", "full_name": "Lance Kendricks", "team": "STL", "player_id": "00-0027985", "gsis_name": "L.Kendricks", "profile_url": "http://www.nfl.com/player/lancekendricks/2495187/profile", "name": "Lance Kendricks"}, {"years_pro": 6, "status": "ACT", "first_name": "James", "last_name": "Laurinaitis", "gsis_id": "00-0027011", "weight": 248, "position": "MLB", "playerid": "00-0027011", "profile_id": 79850, "number": 55, "uniform_number": 55, "height": 74, "esb_id": "LAU629310", "college": "Ohio State", "birthdate": "12/3/1986", "full_name": "James Laurinaitis", "team": "STL", "player_id": "00-0027011", "gsis_name": "J.Laurinaitis", "profile_url": "http://www.nfl.com/player/jameslaurinaitis/79850/profile", "name": "James Laurinaitis"}, {"years_pro": 4, "status": "ACT", "first_name": "Austin", "last_name": "Pettis", "gsis_id": "00-0028016", "weight": 203, "position": "WR", "playerid": "00-0028016", "profile_id": 2495212, "number": 18, "uniform_number": 18, "height": 75, "esb_id": "PET735733", "college": "Boise State", "birthdate": "2/8/1988", "full_name": "Austin Pettis", "team": "STL", "player_id": "00-0028016", "gsis_name": "A.Pettis", "profile_url": "http://www.nfl.com/player/austinpettis/2495212/profile", "name": "Austin Pettis"}, {"years_pro": 2, "status": "ACT", "first_name": "Cody", "last_name": "Davis", "gsis_id": "00-0029764", "weight": 206, "position": "DB", "playerid": "00-0029764", "profile_id": 2541135, "number": 38, "uniform_number": 38, "height": 73, "esb_id": "DAV247918", "college": "Texas Tech", "birthdate": "6/6/1989", "full_name": "Cody Davis", "team": "STL", "player_id": "00-0029764", "gsis_name": "C.Davis", "profile_url": "http://www.nfl.com/player/codydavis/2541135/profile", "name": "Cody Davis"}, {"years_pro": 11, "status": "ACT", "first_name": "Scott", "last_name": "Wells", "gsis_id": "00-0022832", "weight": 302, "position": "C", "playerid": "00-0022832", "profile_id": 2506025, "number": 63, "uniform_number": 63, "height": 74, "esb_id": "WEL588327", "college": "Tennessee", "birthdate": "1/7/1981", "full_name": "Scott Wells", "team": "STL", "player_id": "00-0022832", "gsis_name": "S.Wells", "profile_url": "http://www.nfl.com/player/scottwells/2506025/profile", "name": "Scott Wells"}, {"years_pro": 3, "status": "ACT", "first_name": "Chris", "last_name": "Givens", "gsis_id": "00-0029614", "weight": 203, "position": "WR", "playerid": "00-0029614", "profile_id": 2535634, "number": 13, "uniform_number": 13, "height": 72, "esb_id": "GIV226674", "college": "Wake Forest", "birthdate": "12/6/1989", "full_name": "Chris Givens", "team": "STL", "player_id": "00-0029614", "gsis_name": "C.Givens", "profile_url": "http://www.nfl.com/player/chrisgivens/2535634/profile", "name": "Chris Givens"}, {"years_pro": 2, "status": "ACT", "first_name": "Ray-Ray", "last_name": "Armstrong", "gsis_id": "00-0030050", "weight": 234, "position": "LB", "playerid": "00-0030050", "profile_id": 2541792, "number": 50, "uniform_number": 50, "height": 75, "esb_id": "ARM649391", "college": "Miami (Fla.)", "birthdate": "3/5/1991", "full_name": "Ray-Ray Armstrong", "team": "STL", "player_id": "00-0030050", "gsis_name": "R.Armstrong", "profile_url": "http://www.nfl.com/player/ray-rayarmstrong/2541792/profile", "name": "Ray-Ray Armstrong"}, {"years_pro": 7, "status": "ACT", "first_name": "Kendall", "last_name": "Langford", "gsis_id": "00-0026206", "weight": 313, "position": "DT", "playerid": "00-0026206", "profile_id": 270, "number": 98, "uniform_number": 98, "height": 78, "esb_id": "LAN553691", "college": "Hampton", "birthdate": "1/27/1986", "full_name": "Kendall Langford", "team": "STL", "player_id": "00-0026206", "gsis_name": "K.Langford", "profile_url": "http://www.nfl.com/player/kendalllangford/270/profile", "name": "Kendall Langford"}, {"years_pro": 3, "status": "ACT", "first_name": "Tim", "last_name": "Barnes", "gsis_id": "00-0028274", "weight": 306, "position": "C", "playerid": "00-0028274", "profile_id": 2530479, "number": 61, "uniform_number": 61, "height": 76, "esb_id": "BAR378906", "college": "Missouri", "birthdate": "5/14/1988", "full_name": "Tim Barnes", "team": "STL", "player_id": "00-0028274", "gsis_name": "T.Barnes", "profile_url": "http://www.nfl.com/player/timbarnes/2530479/profile", "name": "Tim Barnes"}, {"years_pro": 2, "status": "ACT", "first_name": "Case", "last_name": "Keenum", "gsis_id": "00-0028986", "weight": 205, "position": "QB", "playerid": "00-0028986", "profile_id": 2532888, "number": 17, "uniform_number": 17, "height": 73, "esb_id": "KEE690598", "college": "Houston", "birthdate": "2/17/1988", "full_name": "Case Keenum", "team": "STL", "player_id": "00-0028986", "gsis_name": "C.Keenum", "profile_url": "http://www.nfl.com/player/casekeenum/2532888/profile", "name": "Case Keenum"}, {"years_pro": 3, "status": "ACT", "first_name": "Michael", "last_name": "Brockers", "gsis_id": "00-0029630", "weight": 326, "position": "DT", "playerid": "00-0029630", "profile_id": 2533050, "number": 90, "uniform_number": 90, "height": 77, "esb_id": "BRO060116", "college": "LSU", "birthdate": "12/21/1990", "full_name": "Michael Brockers", "team": "STL", "player_id": "00-0029630", "gsis_name": "M.Brockers", "profile_url": "http://www.nfl.com/player/michaelbrockers/2533050/profile", "name": "Michael Brockers"}, {"years_pro": 7, "status": "ACT", "first_name": "Jo-Lonn", "last_name": "Dunbar", "gsis_id": "00-0025838", "weight": 235, "position": "OLB", "playerid": "00-0025838", "profile_id": 224, "number": 58, "uniform_number": 58, "height": 72, "esb_id": "DUN097263", "college": "Boston College", "birthdate": "3/13/1985", "full_name": "Jo-Lonn Dunbar", "team": "STL", "player_id": "00-0025838", "gsis_name": "J.Dunbar", "profile_url": "http://www.nfl.com/player/jo-lonndunbar/224/profile", "name": "Jo-Lonn Dunbar"}, {"years_pro": 2, "status": "ACT", "first_name": "Brandon", "last_name": "McGee", "gsis_id": "00-0030535", "weight": 193, "position": "CB", "playerid": "00-0030535", "profile_id": 2539989, "number": 32, "uniform_number": 32, "height": 71, "esb_id": "MCG092837", "college": "Miami (Fla.)", "birthdate": "12/11/1990", "full_name": "Brandon McGee", "team": "STL", "player_id": "00-0030535", "gsis_name": "B.McGee", "profile_url": "http://www.nfl.com/player/brandonmcgee/2539989/profile", "name": "Brandon McGee"}, {"years_pro": 2, "status": "ACT", "first_name": "T.J.", "last_name": "McDonald", "gsis_id": "00-0030530", "weight": 217, "position": "SS", "playerid": "00-0030530", "profile_id": 2539309, "number": 25, "uniform_number": 25, "height": 74, "esb_id": "MCD574475", "college": "USC", "birthdate": "1/26/1991", "full_name": "T.J. McDonald", "team": "STL", "player_id": "00-0030530", "gsis_name": "T.McDonald", "profile_url": "http://www.nfl.com/player/t.j.mcdonald/2539309/profile", "name": "T.J. McDonald"}, {"years_pro": 2, "status": "ACT", "first_name": "Zac", "last_name": "Stacy", "gsis_id": "00-0030536", "weight": 224, "position": "RB", "playerid": "00-0030536", "profile_id": 2540273, "number": 30, "uniform_number": 30, "height": 69, "esb_id": "STA100025", "college": "Vanderbilt", "birthdate": "4/9/1991", "full_name": "Zac Stacy", "team": "STL", "player_id": "00-0030536", "gsis_name": "Z.Stacy", "profile_url": "http://www.nfl.com/player/zacstacy/2540273/profile", "name": "Zac Stacy"}, {"years_pro": 2, "status": "ACT", "first_name": "Barrett", "last_name": "Jones", "gsis_id": "00-0030534", "weight": 308, "position": "OG", "playerid": "00-0030534", "profile_id": 2539195, "number": 67, "uniform_number": 67, "height": 76, "esb_id": "JON075575", "college": "Alabama", "birthdate": "5/25/1990", "full_name": "Barrett Jones", "team": "STL", "player_id": "00-0030534", "gsis_name": "B.Jones", "profile_url": "http://www.nfl.com/player/barrettjones/2539195/profile", "name": "Barrett Jones"}, {"years_pro": 7, "status": "ACT", "first_name": "William", "last_name": "Hayes", "gsis_id": "00-0026243", "weight": 278, "position": "DE", "playerid": "00-0026243", "profile_id": 4483, "number": 95, "uniform_number": 95, "height": 75, "esb_id": "HAY474225", "college": "Winston-Salem State", "birthdate": "5/2/1985", "full_name": "William Hayes", "team": "STL", "player_id": "00-0026243", "gsis_name": "W.Hayes", "profile_url": "http://www.nfl.com/player/williamhayes/4483/profile", "name": "William Hayes"}, {"years_pro": 0, "status": "ACT", "first_name": "Aaron", "last_name": "Donald", "gsis_id": "00-0031388", "weight": 285, "position": "DT", "playerid": "00-0031388", "profile_id": 2543485, "number": 99, "uniform_number": 99, "height": 73, "esb_id": "DON134977", "college": "Pittsburgh", "birthdate": "5/23/1991", "full_name": "Aaron Donald", "team": "STL", "player_id": "00-0031388", "gsis_name": "", "profile_url": "http://www.nfl.com/player/aarondonald/2543485/profile", "name": "Aaron Donald"}, {"years_pro": 0, "status": "ACT", "first_name": "Lamarcus", "last_name": "Joyner", "gsis_id": "00-0031389", "weight": 184, "position": "CB", "playerid": "00-0031389", "profile_id": 2543492, "number": 20, "uniform_number": 20, "height": 68, "esb_id": "JOY464866", "college": "Florida State", "birthdate": "11/27/1990", "full_name": "Lamarcus Joyner", "team": "STL", "player_id": "00-0031389", "gsis_name": "L.Joyner", "profile_url": "http://www.nfl.com/player/lamarcusjoyner/2543492/profile", "name": "Lamarcus Joyner"}, {"years_pro": 0, "status": "ACT", "first_name": "Greg", "last_name": "Robinson", "gsis_id": "00-0031386", "weight": 332, "position": "OT", "playerid": "00-0031386", "profile_id": 2543458, "number": 79, "uniform_number": 79, "height": 77, "esb_id": "ROB501818", "college": "Auburn", "birthdate": "10/21/1992", "full_name": "Greg Robinson", "team": "STL", "player_id": "00-0031386", "gsis_name": "", "profile_url": "http://www.nfl.com/player/gregrobinson/2543458/profile", "name": "Greg Robinson"}, {"years_pro": 2, "status": "ACT", "first_name": "Alec", "last_name": "Ogletree", "gsis_id": "00-0030527", "weight": 245, "position": "OLB", "playerid": "00-0030527", "profile_id": 2540143, "number": 52, "uniform_number": 52, "height": 74, "esb_id": "OGL654714", "college": "Georgia", "birthdate": "9/25/1991", "full_name": "Alec Ogletree", "team": "STL", "player_id": "00-0030527", "gsis_name": "A.Ogletree", "profile_url": "http://www.nfl.com/player/alecogletree/2540143/profile", "name": "Alec Ogletree"}, {"years_pro": 3, "status": "ACT", "first_name": "Trumaine", "last_name": "Johnson", "gsis_id": "00-0029690", "weight": 208, "position": "CB", "playerid": "00-0029690", "profile_id": 2532877, "number": 22, "uniform_number": 22, "height": 74, "esb_id": "JOH708747", "college": "Montana", "birthdate": "1/1/1990", "full_name": "Trumaine Johnson", "team": "STL", "player_id": "00-0029690", "gsis_name": "T.Johnson", "profile_url": "http://www.nfl.com/player/trumainejohnson/2532877/profile", "name": "Trumaine Johnson"}, {"years_pro": 2, "status": "ACT", "first_name": "Tavon", "last_name": "Austin", "gsis_id": "00-0030525", "weight": 176, "position": "WR", "playerid": "00-0030525", "profile_id": 2539336, "number": 11, "uniform_number": 11, "height": 68, "esb_id": "AUS659596", "college": "West Virginia", "birthdate": "3/15/1991", "full_name": "Tavon Austin", "team": "STL", "player_id": "00-0030525", "gsis_name": "T.Austin", "profile_url": "http://www.nfl.com/player/tavonaustin/2539336/profile", "name": "Tavon Austin"}, {"years_pro": 7, "status": "RES", "first_name": "Chris", "last_name": "Long", "gsis_id": "00-0026142", "weight": 268, "position": "DE", "playerid": "00-0026142", "profile_id": 276, "number": 91, "uniform_number": 91, "height": 75, "esb_id": "LON213256", "college": "Virginia", "birthdate": "3/28/1985", "full_name": "Chris Long", "team": "STL", "player_id": "00-0026142", "gsis_name": "C.Long", "profile_url": "http://www.nfl.com/player/chrislong/276/profile", "name": "Chris Long"}, {"years_pro": 0, "status": "ACT", "first_name": "Alex", "last_name": "Bayer", "gsis_id": "00-0030975", "weight": 258, "position": "TE", "playerid": "00-0030975", "profile_id": 2550424, "number": 82, "uniform_number": 82, "height": 76, "esb_id": "BAY012833", "college": "Bowling Green State", "birthdate": "11/8/1990", "full_name": "Alex Bayer", "team": "STL", "player_id": "00-0030975", "gsis_name": "A.Bayer", "profile_url": "http://www.nfl.com/player/alexbayer/2550424/profile", "name": "Alex Bayer"}, {"years_pro": 5, "status": "RES", "first_name": "Sam", "last_name": "Bradford", "gsis_id": "00-0027854", "weight": 224, "position": "QB", "playerid": "00-0027854", "profile_id": 497095, "number": 8, "uniform_number": 8, "height": 76, "esb_id": "BRA101548", "college": "Oklahoma", "birthdate": "11/8/1987", "full_name": "Sam Bradford", "team": "STL", "player_id": "00-0027854", "gsis_name": "S.Bradford", "profile_url": "http://www.nfl.com/player/sambradford/497095/profile", "name": "Sam Bradford"}, {"years_pro": 13, "status": "ACT", "first_name": "Shaun", "last_name": "Hill", "gsis_id": "00-0020679", "weight": 220, "position": "QB", "playerid": "00-0020679", "profile_id": 2504833, "number": 14, "uniform_number": 14, "height": 75, "esb_id": "HIL586565", "college": "Maryland", "birthdate": "1/9/1980", "full_name": "Shaun Hill", "team": "STL", "player_id": "00-0020679", "gsis_name": "S.Hill", "profile_url": "http://www.nfl.com/player/shaunhill/2504833/profile", "name": "Shaun Hill"}, {"years_pro": 4, "status": "ACT", "first_name": "Rodger", "last_name": "Saffold", "gsis_id": "00-0027648", "weight": 332, "position": "G", "playerid": "00-0027648", "profile_id": 497048, "number": 76, "uniform_number": 76, "height": 77, "esb_id": "SAF408541", "college": "Indiana", "birthdate": "6/6/1988", "full_name": "Rodger Saffold", "team": "STL", "player_id": "00-0027648", "gsis_name": "R.Saffold", "profile_url": "http://www.nfl.com/player/rodgersaffold/497048/profile", "name": "Rodger Saffold"}, {"years_pro": 2, "status": "ACT", "first_name": "Daren", "last_name": "Bates", "gsis_id": "00-0029794", "weight": 225, "position": "LB", "playerid": "00-0029794", "profile_id": 2541539, "number": 53, "uniform_number": 53, "height": 71, "esb_id": "BAT105064", "college": "Auburn", "birthdate": "11/27/1990", "full_name": "Daren Bates", "team": "STL", "player_id": "00-0029794", "gsis_name": "D.Bates", "profile_url": "http://www.nfl.com/player/darenbates/2541539/profile", "name": "Daren Bates"}, {"years_pro": 2, "status": "ACT", "first_name": "Benny", "last_name": "Cunningham", "gsis_id": "00-0029795", "weight": 217, "position": "RB", "playerid": "00-0029795", "profile_id": 2541544, "number": 36, "uniform_number": 36, "height": 70, "esb_id": "CUN106619", "college": "Middle Tennessee State", "birthdate": "7/7/1990", "full_name": "Benny Cunningham", "team": "STL", "player_id": "00-0029795", "gsis_name": "B.Cunningham", "profile_url": "http://www.nfl.com/player/bennycunningham/2541544/profile", "name": "Benny Cunningham"}, {"years_pro": 2, "status": "ACT", "first_name": "Chase", "last_name": "Reynolds", "gsis_id": "00-0028795", "weight": 205, "position": "RB", "playerid": "00-0028795", "profile_id": 2531218, "number": 34, "uniform_number": 34, "height": 72, "esb_id": "REY105214", "college": "Montana", "birthdate": "10/22/1987", "full_name": "Chase Reynolds", "team": "STL", "player_id": "00-0028795", "gsis_name": "C.Reynolds", "profile_url": "http://www.nfl.com/player/chasereynolds/2531218/profile", "name": "Chase Reynolds"}, {"years_pro": 4, "status": "ACT", "first_name": "Mike", "last_name": "Person", "gsis_id": "00-0028177", "weight": 299, "position": "T", "playerid": "00-0028177", "profile_id": 2508140, "number": 73, "uniform_number": 73, "height": 76, "esb_id": "PER822092", "college": "Montana State", "birthdate": "6/17/1988", "full_name": "Mike Person", "team": "STL", "player_id": "00-0028177", "gsis_name": "M.Person", "profile_url": "http://www.nfl.com/player/mikeperson/2508140/profile", "name": "Mike Person"}, {"years_pro": 6, "status": "ACT", "first_name": "Kenny", "last_name": "Britt", "gsis_id": "00-0027006", "weight": 223, "position": "WR", "playerid": "00-0027006", "profile_id": 71217, "number": 81, "uniform_number": 81, "height": 75, "esb_id": "BRI708216", "college": "Rutgers", "birthdate": "9/19/1988", "full_name": "Kenny Britt", "team": "STL", "player_id": "00-0027006", "gsis_name": "K.Britt", "profile_url": "http://www.nfl.com/player/kennybritt/71217/profile", "name": "Kenny Britt"}, {"years_pro": 3, "status": "ACT", "first_name": "Brian", "last_name": "Quick", "gsis_id": "00-0029640", "weight": 218, "position": "WR", "playerid": "00-0029640", "profile_id": 2532933, "number": 83, "uniform_number": 83, "height": 75, "esb_id": "QUI043372", "college": "Appalachian State", "birthdate": "6/5/1989", "full_name": "Brian Quick", "team": "STL", "player_id": "00-0029640", "gsis_name": "B.Quick", "profile_url": "http://www.nfl.com/player/brianquick/2532933/profile", "name": "Brian Quick"}, {"years_pro": 1, "status": "RES", "first_name": "Mason", "last_name": "Brodine", "gsis_id": "00-0028755", "weight": 284, "position": "TE", "playerid": "00-0028755", "profile_id": 2531154, "number": 86, "uniform_number": 86, "height": 79, "esb_id": "BRO086802", "college": "Nebraska-Kearney", "birthdate": "2/18/1988", "full_name": "Mason Brodine", "team": "STL", "player_id": "00-0028755", "gsis_name": "M.Brodine", "profile_url": "http://www.nfl.com/player/masonbrodine/2531154/profile", "name": "Mason Brodine"}, {"years_pro": 3, "status": "RES", "first_name": "Isaiah", "last_name": "Pead", "gsis_id": "00-0029626", "weight": 204, "position": "RB", "playerid": "00-0029626", "profile_id": 2532926, "number": 24, "uniform_number": 24, "height": 70, "esb_id": "PEA141066", "college": "Cincinnati", "birthdate": "12/14/1989", "full_name": "Isaiah Pead", "team": "STL", "player_id": "00-0029626", "gsis_name": "I.Pead", "profile_url": "http://www.nfl.com/player/isaiahpead/2532926/profile", "name": "Isaiah Pead"}, {"years_pro": 4, "status": "ACT", "first_name": "Robert", "last_name": "Quinn", "gsis_id": "00-0027952", "weight": 264, "position": "DE", "playerid": "00-0027952", "profile_id": 2495485, "number": 94, "uniform_number": 94, "height": 76, "esb_id": "QUI715221", "college": "North Carolina", "birthdate": "5/18/1990", "full_name": "Robert Quinn", "team": "STL", "player_id": "00-0027952", "gsis_name": "R.Quinn", "profile_url": "http://www.nfl.com/player/robertquinn/2495485/profile", "name": "Robert Quinn"}, {"years_pro": 6, "status": "ACT", "first_name": "Jared", "last_name": "Cook", "gsis_id": "00-0027061", "weight": 254, "position": "TE", "playerid": "00-0027061", "profile_id": 71265, "number": 89, "uniform_number": 89, "height": 77, "esb_id": "COO152641", "college": "South Carolina", "birthdate": "4/7/1987", "full_name": "Jared Cook", "team": "STL", "player_id": "00-0027061", "gsis_name": "J.Cook", "profile_url": "http://www.nfl.com/player/jaredcook/71265/profile", "name": "Jared Cook"}, {"years_pro": 3, "status": "ACT", "first_name": "Greg", "last_name": "Zuerlein", "gsis_id": "00-0029621", "weight": 196, "position": "K", "playerid": "00-0029621", "profile_id": 2534797, "number": 4, "uniform_number": 4, "height": 72, "esb_id": "ZUE563610", "college": "Missouri Western State", "birthdate": "12/27/1987", "full_name": "Greg Zuerlein", "team": "STL", "player_id": "00-0029621", "gsis_name": "G.Zuerlein", "profile_url": "http://www.nfl.com/player/gregzuerlein/2534797/profile", "name": "Greg Zuerlein"}, {"years_pro": 7, "status": "ACT", "first_name": "Jake", "last_name": "Long", "gsis_id": "00-0025820", "weight": 322, "position": "T", "playerid": "00-0025820", "profile_id": 278, "number": 77, "uniform_number": 77, "height": 79, "esb_id": "LON319884", "college": "Michigan", "birthdate": "5/9/1985", "full_name": "Jake Long", "team": "STL", "player_id": "00-0025820", "gsis_name": "J.Long", "profile_url": "http://www.nfl.com/player/jakelong/278/profile", "name": "Jake Long"}, {"years_pro": 4, "status": "ACT", "first_name": "Joe", "last_name": "Barksdale", "gsis_id": "00-0028030", "weight": 326, "position": "T", "playerid": "00-0028030", "profile_id": 2508117, "number": 72, "uniform_number": 72, "height": 77, "esb_id": "BAR194643", "college": "LSU", "birthdate": "1/1/1988", "full_name": "Joe Barksdale", "team": "STL", "player_id": "00-0028030", "gsis_name": "J.Barksdale", "profile_url": "http://www.nfl.com/player/joebarksdale/2508117/profile", "name": "Joe Barksdale"}, {"years_pro": 5, "status": "ACT", "first_name": "Eugene", "last_name": "Sims", "gsis_id": "00-0027787", "weight": 269, "position": "DE", "playerid": "00-0027787", "profile_id": 1037852, "number": 97, "uniform_number": 97, "height": 78, "esb_id": "SIM697600", "college": "West Texas A&M", "birthdate": "3/18/1986", "full_name": "Eugene Sims", "team": "STL", "player_id": "00-0027787", "gsis_name": "E.Sims", "profile_url": "http://www.nfl.com/player/eugenesims/1037852/profile", "name": "Eugene Sims"}, {"years_pro": 2, "status": "ACT", "first_name": "Austin", "last_name": "Davis", "gsis_id": "00-0028957", "weight": 221, "position": "QB", "playerid": "00-0028957", "profile_id": 2533349, "number": 9, "uniform_number": 9, "height": 74, "esb_id": "DAV164136", "college": "Southern Mississippi", "birthdate": "6/2/1989", "full_name": "Austin Davis", "team": "STL", "player_id": "00-0028957", "gsis_name": "A.Davis", "profile_url": "http://www.nfl.com/player/austindavis/2533349/profile", "name": "Austin Davis"}, {"years_pro": 3, "status": "ACT", "first_name": "Cory", "last_name": "Harkey", "gsis_id": "00-0028958", "weight": 259, "position": "TE", "playerid": "00-0028958", "profile_id": 2533353, "number": 46, "uniform_number": 46, "height": 76, "esb_id": "HAR162438", "college": "UCLA", "birthdate": "6/17/1990", "full_name": "Cory Harkey", "team": "STL", "player_id": "00-0028958", "gsis_name": "C.Harkey", "profile_url": "http://www.nfl.com/player/coryharkey/2533353/profile", "name": "Cory Harkey"}, {"years_pro": 2, "status": "SUS", "first_name": "Stedman", "last_name": "Bailey", "gsis_id": "00-0030532", "weight": 194, "position": "WR", "playerid": "00-0030532", "profile_id": 2540157, "number": 12, "uniform_number": 12, "height": 70, "esb_id": "BAI627251", "college": "West Virginia", "birthdate": "11/11/1990", "full_name": "Stedman Bailey", "team": "STL", "player_id": "00-0030532", "gsis_name": "S.Bailey", "profile_url": "http://www.nfl.com/player/stedmanbailey/2540157/profile", "name": "Stedman Bailey"}, {"years_pro": 3, "status": "ACT", "first_name": "Janoris", "last_name": "Jenkins", "gsis_id": "00-0029681", "weight": 198, "position": "CB", "playerid": "00-0029681", "profile_id": 2532875, "number": 21, "uniform_number": 21, "height": 70, "esb_id": "JEN268608", "college": "North Alabama", "birthdate": "10/29/1988", "full_name": "Janoris Jenkins", "team": "STL", "player_id": "00-0029681", "gsis_name": "J.Jenkins", "profile_url": "http://www.nfl.com/player/janorisjenkins/2532875/profile", "name": "Janoris Jenkins"}, {"years_pro": 0, "status": "RES", "first_name": "Demetrius", "last_name": "Rhaney", "gsis_id": "00-0031399", "weight": 301, "position": "C", "playerid": "00-0031399", "profile_id": 2549991, "number": 65, "uniform_number": 65, "height": 74, "esb_id": "RHA444955", "college": "Tennessee State", "birthdate": "6/22/1992", "full_name": "Demetrius Rhaney", "team": "STL", "player_id": "00-0031399", "gsis_name": "D.Rhaney", "profile_url": "http://www.nfl.com/player/demetriusrhaney/2549991/profile", "name": "Demetrius Rhaney"}, {"years_pro": 0, "status": "ACT", "first_name": "E.J.", "last_name": "Gaines", "gsis_id": "00-0031394", "weight": 190, "position": "CB", "playerid": "00-0031394", "profile_id": 2543823, "number": 33, "uniform_number": 33, "height": 70, "esb_id": "GAI292759", "college": "Missouri", "birthdate": "2/23/1992", "full_name": "E.J. Gaines", "team": "STL", "player_id": "00-0031394", "gsis_name": "E.Gaines", "profile_url": "http://www.nfl.com/player/e.j.gaines/2543823/profile", "name": "E.J. Gaines"}, {"years_pro": 0, "status": "ACT", "first_name": "Tre", "last_name": "Mason", "gsis_id": "00-0031391", "weight": 207, "position": "RB", "playerid": "00-0031391", "profile_id": 2543502, "number": 27, "uniform_number": 27, "height": 68, "esb_id": "MAS269896", "college": "Auburn", "birthdate": "8/6/1993", "full_name": "Tre Mason", "team": "STL", "player_id": "00-0031391", "gsis_name": "T.Mason", "profile_url": "http://www.nfl.com/player/tremason/2543502/profile", "name": "Tre Mason"}, {"years_pro": 0, "status": "ACT", "first_name": "Maurice", "last_name": "Alexander", "gsis_id": "00-0031393", "weight": 220, "position": "SS", "playerid": "00-0031393", "profile_id": 2550145, "number": 31, "uniform_number": 31, "height": 73, "esb_id": "ALE513150", "college": "Utah State", "birthdate": "2/16/1991", "full_name": "Maurice Alexander", "team": "STL", "player_id": "00-0031393", "gsis_name": "M.Alexander", "profile_url": "http://www.nfl.com/player/mauricealexander/2550145/profile", "name": "Maurice Alexander"}, {"years_pro": 0, "status": "ACT", "first_name": "Ethan", "last_name": "Westbrooks", "gsis_id": "00-0030986", "weight": 267, "position": "DT", "playerid": "00-0030986", "profile_id": 2550449, "number": 93, "uniform_number": 93, "height": 76, "esb_id": "WES590634", "college": "West Texas A&M", "birthdate": "11/15/1990", "full_name": "Ethan Westbrooks", "team": "STL", "player_id": "00-0030986", "gsis_name": "E.Westbrooks", "profile_url": "http://www.nfl.com/player/ethanwestbrooks/2550449/profile", "name": "Ethan Westbrooks"}, {"years_pro": 0, "status": "ACT", "first_name": "Trey", "last_name": "Watts", "gsis_id": "00-0030985", "weight": 208, "position": "RB", "playerid": "00-0030985", "profile_id": 2550448, "number": 42, "uniform_number": 42, "height": 69, "esb_id": "WAT728732", "college": "Tulsa", "birthdate": "2/13/1991", "full_name": "Trey Watts", "team": "STL", "player_id": "00-0030985", "gsis_name": "", "profile_url": "http://www.nfl.com/player/treywatts/2550448/profile", "name": "Trey Watts"}, {"years_pro": 0, "status": "ACT", "first_name": "Marcus", "last_name": "Roberson", "gsis_id": "00-0030982", "weight": 191, "position": "CB", "playerid": "00-0030982", "profile_id": 2550442, "number": 47, "uniform_number": 47, "height": 72, "esb_id": "ROB083134", "college": "Florida", "birthdate": "10/4/1992", "full_name": "Marcus Roberson", "team": "STL", "player_id": "00-0030982", "gsis_name": "M.Roberson", "profile_url": "http://www.nfl.com/player/marcusroberson/2550442/profile", "name": "Marcus Roberson"}, {"years_pro": 4, "status": "ACT", "first_name": "Jake", "last_name": "McQuaide", "gsis_id": "00-0028394", "weight": 244, "position": "LS", "playerid": "00-0028394", "profile_id": 2530852, "number": 44, "uniform_number": 44, "height": 74, "esb_id": "MCQ288110", "college": "Ohio State", "birthdate": "12/7/1987", "full_name": "Jake McQuaide", "team": "STL", "player_id": "00-0028394", "gsis_name": "J.McQuaide", "profile_url": "http://www.nfl.com/player/jakemcquaide/2530852/profile", "name": "Jake McQuaide"}]