[{"years_pro": 4, "status": "ACT", "first_name": "Niles", "last_name": "Paul", "gsis_id": "00-0028093", "weight": 241, "position": "TE", "playerid": "00-0028093", "profile_id": 2495211, "number": 84, "uniform_number": 84, "height": 73, "esb_id": "PAU265785", "college": "Nebraska", "birthdate": "8/9/1989", "full_name": "Niles Paul", "team": "WAS", "player_id": "00-0028093", "gsis_name": "N.Paul", "profile_url": "http://www.nfl.com/player/nilespaul/2495211/profile", "name": "Niles Paul"}, {"years_pro": 0, "status": "RES", "first_name": "Courtney", "last_name": "Bridget", "gsis_id": "00-0031200", "weight": 195, "position": "DB", "playerid": "00-0031200", "profile_id": 2550612, "number": 0, "uniform_number": 0, "height": 75, "esb_id": "BRI128262", "college": "Hampton", "birthdate": "3/22/1991", "full_name": "Courtney Bridget", "team": "WAS", "player_id": "00-0031200", "gsis_name": "", "profile_url": "http://www.nfl.com/player/courtneybridget/2550612/profile", "name": "Courtney Bridget"}, {"years_pro": 0, "status": "RES", "first_name": "Jerry", "last_name": "Rice", "gsis_id": "00-0031429", "weight": 185, "position": "WR", "playerid": "00-0031429", "profile_id": 2550936, "number": 0, "uniform_number": 0, "height": 71, "esb_id": "RIC134130", "college": "Nevada-Las Vegas", "birthdate": "7/27/1991", "full_name": "Jerry Rice", "team": "WAS", "player_id": "00-0031429", "gsis_name": "", "profile_url": "http://www.nfl.com/player/jerryrice/2550936/profile", "name": "Jerry Rice"}, {"years_pro": 9, "status": "RES", "first_name": "Barry", "last_name": "Cofield", "gsis_id": "00-0024339", "weight": 303, "position": "NT", "playerid": "00-0024339", "profile_id": 2506926, "number": 96, "uniform_number": 96, "height": 76, "esb_id": "COF756192", "college": "Northwestern", "birthdate": "3/19/1984", "full_name": "Barry Cofield", "team": "WAS", "player_id": "00-0024339", "gsis_name": "B.Cofield", "profile_url": "http://www.nfl.com/player/barrycofield/2506926/profile", "name": "Barry Cofield"}, {"years_pro": 14, "status": "ACT", "first_name": "Santana", "last_name": "Moss", "gsis_id": "00-0020494", "weight": 193, "position": "WR", "playerid": "00-0020494", "profile_id": 2504743, "number": 89, "uniform_number": 89, "height": 70, "esb_id": "MOS717844", "college": "Miami (Fla.)", "birthdate": "6/1/1979", "full_name": "Santana Moss", "team": "WAS", "player_id": "00-0020494", "gsis_name": "S.Moss", "profile_url": "http://www.nfl.com/player/santanamoss/2504743/profile", "name": "Santana Moss"}, {"years_pro": 3, "status": "ACT", "first_name": "Kai", "last_name": "Forbath", "gsis_id": "00-0028787", "weight": 197, "position": "K", "playerid": "00-0028787", "profile_id": 2495150, "number": 2, "uniform_number": 2, "height": 71, "esb_id": "FOR007550", "college": "UCLA", "birthdate": "9/2/1987", "full_name": "Kai Forbath", "team": "WAS", "player_id": "00-0028787", "gsis_name": "K.Forbath", "profile_url": "http://www.nfl.com/player/kaiforbath/2495150/profile", "name": "Kai Forbath"}, {"years_pro": 7, "status": "ACT", "first_name": "Pierre", "last_name": "Garcon", "gsis_id": "00-0026345", "weight": 216, "position": "WR", "playerid": "00-0026345", "profile_id": 2346, "number": 88, "uniform_number": 88, "height": 72, "esb_id": "GAR115573", "college": "Mount Union", "birthdate": "8/8/1986", "full_name": "Pierre Garcon", "team": "WAS", "player_id": "00-0026345", "gsis_name": "P.Garcon", "profile_url": "http://www.nfl.com/player/pierregarcon/2346/profile", "name": "Pierre Garcon"}, {"years_pro": 5, "status": "ACT", "first_name": "Andre", "last_name": "Roberts", "gsis_id": "00-0027691", "weight": 187, "position": "WR", "playerid": "00-0027691", "profile_id": 497320, "number": 12, "uniform_number": 12, "height": 71, "esb_id": "ROB102317", "college": "The Citadel", "birthdate": "1/9/1988", "full_name": "Andre Roberts", "team": "WAS", "player_id": "00-0027691", "gsis_name": "A.Roberts", "profile_url": "http://www.nfl.com/player/andreroberts/497320/profile", "name": "Andre Roberts"}, {"years_pro": 5, "status": "ACT", "first_name": "Shawn", "last_name": "Lauvao", "gsis_id": "00-0027694", "weight": 315, "position": "G", "playerid": "00-0027694", "profile_id": 497028, "number": 77, "uniform_number": 77, "height": 75, "esb_id": "LAU738293", "college": "Arizona State", "birthdate": "10/26/1987", "full_name": "Shawn Lauvao", "team": "WAS", "player_id": "00-0027694", "gsis_name": "S.Lauvao", "profile_url": "http://www.nfl.com/player/shawnlauvao/497028/profile", "name": "Shawn Lauvao"}, {"years_pro": 9, "status": "ACT", "first_name": "Chris", "last_name": "Chester", "gsis_id": "00-0024271", "weight": 303, "position": "G", "playerid": "00-0024271", "profile_id": 2495819, "number": 66, "uniform_number": 66, "height": 75, "esb_id": "CHE592085", "college": "Oklahoma", "birthdate": "1/12/1983", "full_name": "Chris Chester", "team": "WAS", "player_id": "00-0024271", "gsis_name": "C.Chester", "profile_url": "http://www.nfl.com/player/chrischester/2495819/profile", "name": "Chris Chester"}, {"years_pro": 2, "status": "ACT", "first_name": "Bacarri", "last_name": "Rambo", "gsis_id": "00-0030289", "weight": 211, "position": "SS", "playerid": "00-0030289", "profile_id": 2539234, "number": 24, "uniform_number": 24, "height": 72, "esb_id": "RAM021629", "college": "Georgia", "birthdate": "6/27/1990", "full_name": "Bacarri Rambo", "team": "WAS", "player_id": "00-0030289", "gsis_name": "B.Rambo", "profile_url": "http://www.nfl.com/player/bacarrirambo/2539234/profile", "name": "Bacarri Rambo"}, {"years_pro": 3, "status": "ACT", "first_name": "Robert", "last_name": "Griffin III", "gsis_id": "00-0029665", "weight": 222, "position": "QB", "playerid": "00-0029665", "profile_id": 2533033, "number": 10, "uniform_number": 10, "height": 74, "esb_id": "GRI283140", "college": "Baylor", "birthdate": "2/12/1990", "full_name": "Robert Griffin III", "team": "WAS", "player_id": "00-0029665", "gsis_name": "R.Griffin", "profile_url": "http://www.nfl.com/player/robertgriffiniii/2533033/profile", "name": "Robert Griffin III"}, {"years_pro": 8, "status": "ACT", "first_name": "Akeem", "last_name": "Jordan", "gsis_id": "00-0025719", "weight": 255, "position": "ILB", "playerid": "00-0025719", "profile_id": 2507285, "number": 54, "uniform_number": 54, "height": 73, "esb_id": "JOR014362", "college": "James Madison", "birthdate": "8/17/1985", "full_name": "Akeem Jordan", "team": "WAS", "player_id": "00-0025719", "gsis_name": "A.Jordan", "profile_url": "http://www.nfl.com/player/akeemjordan/2507285/profile", "name": "Akeem Jordan"}, {"years_pro": 0, "status": "ACT", "first_name": "Trent", "last_name": "Murphy", "gsis_id": "00-0031300", "weight": 258, "position": "LB", "playerid": "00-0031300", "profile_id": 2543503, "number": 93, "uniform_number": 93, "height": 77, "esb_id": "MUR524597", "college": "Stanford", "birthdate": "12/20/1990", "full_name": "Trent Murphy", "team": "WAS", "player_id": "00-0031300", "gsis_name": "T.Murphy", "profile_url": "http://www.nfl.com/player/trentmurphy/2543503/profile", "name": "Trent Murphy"}, {"years_pro": 2, "status": "ACT", "first_name": "David", "last_name": "Amerson", "gsis_id": "00-0030420", "weight": 205, "position": "CB", "playerid": "00-0030420", "profile_id": 2540170, "number": 39, "uniform_number": 39, "height": 73, "esb_id": "AME404790", "college": "North Carolina State", "birthdate": "12/8/1991", "full_name": "David Amerson", "team": "WAS", "player_id": "00-0030420", "gsis_name": "D.Amerson", "profile_url": "http://www.nfl.com/player/davidamerson/2540170/profile", "name": "David Amerson"}, {"years_pro": 8, "status": "ACT", "first_name": "Adam", "last_name": "Hayward", "gsis_id": "00-0025569", "weight": 240, "position": "OLB", "playerid": "00-0025569", "profile_id": 2507229, "number": 55, "uniform_number": 55, "height": 73, "esb_id": "HAY776168", "college": "Portland State", "birthdate": "6/23/1984", "full_name": "Adam Hayward", "team": "WAS", "player_id": "00-0025569", "gsis_name": "A.Hayward", "profile_url": "http://www.nfl.com/player/adamhayward/2507229/profile", "name": "Adam Hayward"}, {"years_pro": 5, "status": "ACT", "first_name": "Darrel", "last_name": "Young", "gsis_id": "00-0026852", "weight": 251, "position": "FB", "playerid": "00-0026852", "profile_id": 2507737, "number": 36, "uniform_number": 36, "height": 71, "esb_id": "YOU170298", "college": "Villanova", "birthdate": "4/8/1987", "full_name": "Darrel Young", "team": "WAS", "player_id": "00-0026852", "gsis_name": "D.Young", "profile_url": "http://www.nfl.com/player/darrelyoung/2507737/profile", "name": "Darrel Young"}, {"years_pro": 13, "status": "ACT", "first_name": "Ryan", "last_name": "Clark", "gsis_id": "00-0020840", "weight": 205, "position": "FS", "playerid": "00-0020840", "profile_id": 2504899, "number": 25, "uniform_number": 25, "height": 71, "esb_id": "CLA544413", "college": "LSU", "birthdate": "10/12/1979", "full_name": "Ryan Clark", "team": "WAS", "player_id": "00-0020840", "gsis_name": "R.Clark", "profile_url": "http://www.nfl.com/player/ryanclark/2504899/profile", "name": "Ryan Clark"}, {"years_pro": 4, "status": "ACT", "first_name": "Roy", "last_name": "Helu", "gsis_id": "00-0028043", "weight": 215, "position": "RB", "playerid": "00-0028043", "profile_id": 2495161, "number": 29, "uniform_number": 29, "height": 71, "esb_id": "HEL697773", "college": "Nebraska", "birthdate": "12/7/1988", "full_name": "Roy Helu", "team": "WAS", "player_id": "00-0028043", "gsis_name": "R.Helu", "profile_url": "http://www.nfl.com/player/royhelu/2495161/profile", "name": "Roy Helu"}, {"years_pro": 0, "status": "ACT", "first_name": "Bashaud", "last_name": "Breeland", "gsis_id": "00-0031052", "weight": 197, "position": "SS", "playerid": "00-0031052", "profile_id": 2543571, "number": 26, "uniform_number": 26, "height": 71, "esb_id": "BRE183598", "college": "Clemson", "birthdate": "1/30/1992", "full_name": "Bashaud Breeland", "team": "WAS", "player_id": "00-0031052", "gsis_name": "B.Breeland", "profile_url": "http://www.nfl.com/player/bashaudbreeland/2543571/profile", "name": "Bashaud Breeland"}, {"years_pro": 6, "status": "ACT", "first_name": "Kory", "last_name": "Lichtensteiger", "gsis_id": "00-0026248", "weight": 296, "position": "C", "playerid": "00-0026248", "profile_id": 274, "number": 78, "uniform_number": 78, "height": 74, "esb_id": "LIC311468", "college": "Bowling Green State", "birthdate": "3/22/1985", "full_name": "Kory Lichtensteiger", "team": "WAS", "player_id": "00-0026248", "gsis_name": "K.Lichtensteiger", "profile_url": "http://www.nfl.com/player/korylichtensteiger/274/profile", "name": "Kory Lichtensteiger"}, {"years_pro": 0, "status": "ACT", "first_name": "Ryan", "last_name": "Grant", "gsis_id": "00-0031068", "weight": 193, "position": "WR", "playerid": "00-0031068", "profile_id": 2543759, "number": 14, "uniform_number": 14, "height": 72, "esb_id": "GRA498062", "college": "Tulane", "birthdate": "12/19/1990", "full_name": "Ryan Grant", "team": "WAS", "player_id": "00-0031068", "gsis_name": "R.Grant", "profile_url": "http://www.nfl.com/player/ryangrant/2543759/profile", "name": "Ryan Grant"}, {"years_pro": 3, "status": "ACT", "first_name": "Duke", "last_name": "Ihenacho", "gsis_id": "00-0028942", "weight": 207, "position": "DB", "playerid": "00-0028942", "profile_id": 2532868, "number": 35, "uniform_number": 35, "height": 73, "esb_id": "IHE454705", "college": "San Jose State", "birthdate": "6/16/1989", "full_name": "Duke Ihenacho", "team": "WAS", "player_id": "00-0028942", "gsis_name": "D.Ihenacho", "profile_url": "http://www.nfl.com/player/dukeihenacho/2532868/profile", "name": "Duke Ihenacho"}, {"years_pro": 3, "status": "ACT", "first_name": "Keenan", "last_name": "Robinson", "gsis_id": "00-0029545", "weight": 238, "position": "ILB", "playerid": "00-0029545", "profile_id": 2532940, "number": 52, "uniform_number": 52, "height": 75, "esb_id": "ROB591898", "college": "Texas", "birthdate": "7/7/1989", "full_name": "Keenan Robinson", "team": "WAS", "player_id": "00-0029545", "gsis_name": "K.Robinson", "profile_url": "http://www.nfl.com/player/keenanrobinson/2532940/profile", "name": "Keenan Robinson"}, {"years_pro": 3, "status": "ACT", "first_name": "Chris", "last_name": "Baker", "gsis_id": "00-0026512", "weight": 325, "position": "DE", "playerid": "00-0026512", "profile_id": 2507557, "number": 92, "uniform_number": 92, "height": 74, "esb_id": "BAK000000", "college": "Hampton", "birthdate": "10/8/1987", "full_name": "Chris Baker", "team": "WAS", "player_id": "00-0026512", "gsis_name": "C.Baker", "profile_url": "http://www.nfl.com/player/chrisbaker/2507557/profile", "name": "Chris Baker"}, {"years_pro": 8, "status": "SUS", "first_name": "Brandon", "last_name": "Meriweather", "gsis_id": "00-0025411", "weight": 197, "position": "SS", "playerid": "00-0025411", "profile_id": 2495678, "number": 31, "uniform_number": 31, "height": 71, "esb_id": "MER280467", "college": "Miami (Fla.)", "birthdate": "1/14/1984", "full_name": "Brandon Meriweather", "team": "WAS", "player_id": "00-0025411", "gsis_name": "B.Meriweather", "profile_url": "http://www.nfl.com/player/brandonmeriweather/2495678/profile", "name": "Brandon Meriweather"}, {"years_pro": 1, "status": "ACT", "first_name": "Will", "last_name": "Compton", "gsis_id": "00-0029869", "weight": 230, "position": "ILB", "playerid": "00-0029869", "profile_id": 2540013, "number": 51, "uniform_number": 51, "height": 73, "esb_id": "COM673597", "college": "Nebraska", "birthdate": "9/19/1989", "full_name": "Will Compton", "team": "WAS", "player_id": "00-0029869", "gsis_name": "W.Compton", "profile_url": "http://www.nfl.com/player/willcompton/2540013/profile", "name": "Will Compton"}, {"years_pro": 11, "status": "ACT", "first_name": "DeAngelo", "last_name": "Hall", "gsis_id": "00-0022923", "weight": 198, "position": "CB", "playerid": "00-0022923", "profile_id": 2506108, "number": 23, "uniform_number": 23, "height": 70, "esb_id": "HAL268837", "college": "Virginia Tech", "birthdate": "11/19/1983", "full_name": "DeAngelo Hall", "team": "WAS", "player_id": "00-0022923", "gsis_name": "D.Hall", "profile_url": "http://www.nfl.com/player/deangelohall/2506108/profile", "name": "DeAngelo Hall"}, {"years_pro": 9, "status": "ACT", "first_name": "Kedric", "last_name": "Golston", "gsis_id": "00-0024410", "weight": 318, "position": "DE", "playerid": "00-0024410", "profile_id": 2506964, "number": 64, "uniform_number": 64, "height": 76, "esb_id": "GOL705804", "college": "Georgia", "birthdate": "5/30/1983", "full_name": "Kedric Golston", "team": "WAS", "player_id": "00-0024410", "gsis_name": "K.Golston", "profile_url": "http://www.nfl.com/player/kedricgolston/2506964/profile", "name": "Kedric Golston"}, {"years_pro": 5, "status": "ACT", "first_name": "Nick", "last_name": "Sundberg", "gsis_id": "00-0026714", "weight": 264, "position": "LS", "playerid": "00-0026714", "profile_id": 2507668, "number": 57, "uniform_number": 57, "height": 72, "esb_id": "SUN263361", "college": "California", "birthdate": "7/29/1987", "full_name": "Nick Sundberg", "team": "WAS", "player_id": "00-0026714", "gsis_name": "N.Sundberg", "profile_url": "http://www.nfl.com/player/nicksundberg/2507668/profile", "name": "Nick Sundberg"}, {"years_pro": 5, "status": "ACT", "first_name": "Trent", "last_name": "Williams", "gsis_id": "00-0027857", "weight": 337, "position": "T", "playerid": "00-0027857", "profile_id": 497073, "number": 71, "uniform_number": 71, "height": 77, "esb_id": "WIL547553", "college": "Oklahoma", "birthdate": "7/19/1988", "full_name": "Trent Williams", "team": "WAS", "player_id": "00-0027857", "gsis_name": "T.Williams", "profile_url": "http://www.nfl.com/player/trentwilliams/497073/profile", "name": "Trent Williams"}, {"years_pro": 5, "status": "SUS", "first_name": "Tanard", "last_name": "Jackson", "gsis_id": "00-0025493", "weight": 193, "position": "DB", "playerid": "00-0025493", "profile_id": 2495643, "number": 36, "uniform_number": 36, "height": 72, "esb_id": "JAC565378", "college": "Syracuse", "birthdate": "7/21/1985", "full_name": "Tanard Jackson", "team": "WAS", "player_id": "00-0025493", "gsis_name": "T.Jackson", "profile_url": "http://www.nfl.com/player/tanardjackson/2495643/profile", "name": "Tanard Jackson"}, {"years_pro": 2, "status": "ACT", "first_name": "Tom", "last_name": "Compton", "gsis_id": "00-0029144", "weight": 308, "position": "T", "playerid": "00-0029144", "profile_id": 2532816, "number": 68, "uniform_number": 68, "height": 77, "esb_id": "COM663097", "college": "South Dakota", "birthdate": "5/10/1989", "full_name": "Tom Compton", "team": "WAS", "player_id": "00-0029144", "gsis_name": "T.Compton", "profile_url": "http://www.nfl.com/player/tomcompton/2532816/profile", "name": "Tom Compton"}, {"years_pro": 3, "status": "ACT", "first_name": "Alfred", "last_name": "Morris", "gsis_id": "00-0029141", "weight": 224, "position": "RB", "playerid": "00-0029141", "profile_id": 2533457, "number": 46, "uniform_number": 46, "height": 70, "esb_id": "MOR317547", "college": "Florida Atlantic", "birthdate": "12/12/1988", "full_name": "Alfred Morris", "team": "WAS", "player_id": "00-0029141", "gsis_name": "A.Morris", "profile_url": "http://www.nfl.com/player/alfredmorris/2533457/profile", "name": "Alfred Morris"}, {"years_pro": 0, "status": "ACT", "first_name": "Akeem", "last_name": "Davis", "gsis_id": "00-0030644", "weight": 200, "position": "DB", "playerid": "00-0030644", "profile_id": 2550022, "number": 35, "uniform_number": 35, "height": 73, "esb_id": "DAV115525", "college": "Memphis", "birthdate": "12/25/1989", "full_name": "Akeem Davis", "team": "WAS", "player_id": "00-0030644", "gsis_name": "A.Davis", "profile_url": "http://www.nfl.com/player/akeemdavis/2550022/profile", "name": "Akeem Davis"}, {"years_pro": 5, "status": "ACT", "first_name": "Colt", "last_name": "McCoy", "gsis_id": "00-0027688", "weight": 215, "position": "QB", "playerid": "00-0027688", "profile_id": 497123, "number": 16, "uniform_number": 16, "height": 73, "esb_id": "MCC603149", "college": "Texas", "birthdate": "9/5/1986", "full_name": "Colt McCoy", "team": "WAS", "player_id": "00-0027688", "gsis_name": "C.McCoy", "profile_url": "http://www.nfl.com/player/coltmccoy/497123/profile", "name": "Colt McCoy"}, {"years_pro": 9, "status": "ACT", "first_name": "Jason", "last_name": "Hatcher", "gsis_id": "00-0024307", "weight": 299, "position": "DE", "playerid": "00-0024307", "profile_id": 2495851, "number": 97, "uniform_number": 97, "height": 78, "esb_id": "HAT099134", "college": "Grambling State", "birthdate": "7/13/1982", "full_name": "Jason Hatcher", "team": "WAS", "player_id": "00-0024307", "gsis_name": "J.Hatcher", "profile_url": "http://www.nfl.com/player/jasonhatcher/2495851/profile", "name": "Jason Hatcher"}, {"years_pro": 6, "status": "ACT", "first_name": "Brian", "last_name": "Orakpo", "gsis_id": "00-0026989", "weight": 257, "position": "OLB", "playerid": "00-0026989", "profile_id": 71423, "number": 98, "uniform_number": 98, "height": 76, "esb_id": "ORA355963", "college": "Texas", "birthdate": "7/31/1986", "full_name": "Brian Orakpo", "team": "WAS", "player_id": "00-0026989", "gsis_name": "B.Orakpo", "profile_url": "http://www.nfl.com/player/brianorakpo/71423/profile", "name": "Brian Orakpo"}, {"years_pro": 7, "status": "ACT", "first_name": "Tracy", "last_name": "Porter", "gsis_id": "00-0026180", "weight": 188, "position": "CB", "playerid": "00-0026180", "profile_id": 2507471, "number": 22, "uniform_number": 22, "height": 71, "esb_id": "POR632160", "college": "Indiana", "birthdate": "8/11/1986", "full_name": "Tracy Porter", "team": "WAS", "player_id": "00-0026180", "gsis_name": "T.Porter", "profile_url": "http://www.nfl.com/player/tracyporter/2507471/profile", "name": "Tracy Porter"}, {"years_pro": 7, "status": "ACT", "first_name": "DeSean", "last_name": "Jackson", "gsis_id": "00-0026189", "weight": 178, "position": "WR", "playerid": "00-0026189", "profile_id": 1581, "number": 11, "uniform_number": 11, "height": 70, "esb_id": "JAC127681", "college": "California", "birthdate": "12/1/1986", "full_name": "DeSean Jackson", "team": "WAS", "player_id": "00-0026189", "gsis_name": "D.Jackson", "profile_url": "http://www.nfl.com/player/deseanjackson/1581/profile", "name": "DeSean Jackson"}, {"years_pro": 3, "status": "ACT", "first_name": "Aldrick", "last_name": "Robinson", "gsis_id": "00-0028116", "weight": 184, "position": "WR", "playerid": "00-0028116", "profile_id": 2495331, "number": 15, "uniform_number": 15, "height": 70, "esb_id": "ROB365875", "college": "Southern Methodist", "birthdate": "11/24/1988", "full_name": "Aldrick Robinson", "team": "WAS", "player_id": "00-0028116", "gsis_name": "A.Robinson", "profile_url": "http://www.nfl.com/player/aldrickrobinson/2495331/profile", "name": "Aldrick Robinson"}, {"years_pro": 4, "status": "ACT", "first_name": "Jarvis", "last_name": "Jenkins", "gsis_id": "00-0027979", "weight": 315, "position": "DE", "playerid": "00-0027979", "profile_id": 2495178, "number": 99, "uniform_number": 99, "height": 76, "esb_id": "JEN269130", "college": "Clemson", "birthdate": "4/24/1988", "full_name": "Jarvis Jenkins", "team": "WAS", "player_id": "00-0027979", "gsis_name": "J.Jenkins", "profile_url": "http://www.nfl.com/player/jarvisjenkins/2495178/profile", "name": "Jarvis Jenkins"}, {"years_pro": 5, "status": "ACT", "first_name": "Perry", "last_name": "Riley", "gsis_id": "00-0027704", "weight": 238, "position": "ILB", "playerid": "00-0027704", "profile_id": 496949, "number": 56, "uniform_number": 56, "height": 72, "esb_id": "RIL545116", "college": "LSU", "birthdate": "5/3/1988", "full_name": "Perry Riley", "team": "WAS", "player_id": "00-0027704", "gsis_name": "P.Riley", "profile_url": "http://www.nfl.com/player/perryriley/496949/profile", "name": "Perry Riley"}, {"years_pro": 5, "status": "RES", "first_name": "Darryl", "last_name": "Sharpton", "gsis_id": "00-0027703", "weight": 235, "position": "ILB", "playerid": "00-0027703", "profile_id": 496951, "number": 53, "uniform_number": 53, "height": 71, "esb_id": "SHA507578", "college": "Miami (Fla.)", "birthdate": "1/1/1988", "full_name": "Darryl Sharpton", "team": "WAS", "player_id": "00-0027703", "gsis_name": "D.Sharpton", "profile_url": "http://www.nfl.com/player/darrylsharpton/496951/profile", "name": "Darryl Sharpton"}, {"years_pro": 3, "status": "ACT", "first_name": "Josh", "last_name": "LeRibeus", "gsis_id": "00-0029666", "weight": 315, "position": "G", "playerid": "00-0029666", "profile_id": 2532891, "number": 67, "uniform_number": 67, "height": 74, "esb_id": "LER296635", "college": "Southern Methodist", "birthdate": "7/2/1989", "full_name": "Josh LeRibeus", "team": "WAS", "player_id": "00-0029666", "gsis_name": "J.LeRibeus", "profile_url": "http://www.nfl.com/player/joshleribeus/2532891/profile", "name": "Josh LeRibeus"}, {"years_pro": 4, "status": "ACT", "first_name": "Ryan", "last_name": "Kerrigan", "gsis_id": "00-0027954", "weight": 260, "position": "OLB", "playerid": "00-0027954", "profile_id": 2495190, "number": 91, "uniform_number": 91, "height": 76, "esb_id": "KER630730", "college": "Purdue", "birthdate": "8/16/1988", "full_name": "Ryan Kerrigan", "team": "WAS", "player_id": "00-0027954", "gsis_name": "R.Kerrigan", "profile_url": "http://www.nfl.com/player/ryankerrigan/2495190/profile", "name": "Ryan Kerrigan"}, {"years_pro": 3, "status": "ACT", "first_name": "Frank", "last_name": "Kearse", "gsis_id": "00-0028169", "weight": 310, "position": "DT", "playerid": "00-0028169", "profile_id": 2499273, "number": 73, "uniform_number": 73, "height": 77, "esb_id": "KEA506049", "college": "Alabama A&M", "birthdate": "10/28/1988", "full_name": "Frank Kearse", "team": "WAS", "player_id": "00-0028169", "gsis_name": "F.Kearse", "profile_url": "http://www.nfl.com/player/frankkearse/2499273/profile", "name": "Frank Kearse"}, {"years_pro": 6, "status": "ACT", "first_name": "E.J.", "last_name": "Biggers", "gsis_id": "00-0026945", "weight": 185, "position": "FS", "playerid": "00-0026945", "profile_id": 238489, "number": 30, "uniform_number": 30, "height": 72, "esb_id": "BIG377790", "college": "Western Michigan", "birthdate": "6/13/1987", "full_name": "E.J. Biggers", "team": "WAS", "player_id": "00-0026945", "gsis_name": "E.Biggers", "profile_url": "http://www.nfl.com/player/e.j.biggers/238489/profile", "name": "E.J. Biggers"}, {"years_pro": 3, "status": "ACT", "first_name": "Kirk", "last_name": "Cousins", "gsis_id": "00-0029604", "weight": 202, "position": "QB", "playerid": "00-0029604", "profile_id": 2532820, "number": 8, "uniform_number": 8, "height": 75, "esb_id": "COU709400", "college": "Michigan State", "birthdate": "8/19/1988", "full_name": "Kirk Cousins", "team": "WAS", "player_id": "00-0029604", "gsis_name": "K.Cousins", "profile_url": "http://www.nfl.com/player/kirkcousins/2532820/profile", "name": "Kirk Cousins"}, {"years_pro": 2, "status": "ACT", "first_name": "Gabe", "last_name": "Miller", "gsis_id": "00-0028078", "weight": 250, "position": "LB", "playerid": "00-0028078", "profile_id": 2499250, "number": 50, "uniform_number": 50, "height": 75, "esb_id": "MIL273414", "college": "Oregon State", "birthdate": "12/5/1987", "full_name": "Gabe Miller", "team": "WAS", "player_id": "00-0028078", "gsis_name": "G.Miller", "profile_url": "http://www.nfl.com/player/gabemiller/2499250/profile", "name": "Gabe Miller"}, {"years_pro": 3, "status": "ACT", "first_name": "Trenton", "last_name": "Robinson", "gsis_id": "00-0029297", "weight": 195, "position": "DB", "playerid": "00-0029297", "profile_id": 2532939, "number": 34, "uniform_number": 34, "height": 69, "esb_id": "ROB710202", "college": "Michigan State", "birthdate": "2/16/1990", "full_name": "Trenton Robinson", "team": "WAS", "player_id": "00-0029297", "gsis_name": "T.Robinson", "profile_url": "http://www.nfl.com/player/trentonrobinson/2532939/profile", "name": "Trenton Robinson"}, {"years_pro": 5, "status": "ACT", "first_name": "Logan", "last_name": "Paulsen", "gsis_id": "00-0027215", "weight": 261, "position": "TE", "playerid": "00-0027215", "profile_id": 2507828, "number": 82, "uniform_number": 82, "height": 77, "esb_id": "PAU641214", "college": "UCLA", "birthdate": "2/26/1987", "full_name": "Logan Paulsen", "team": "WAS", "player_id": "00-0027215", "gsis_name": "L.Paulsen", "profile_url": "http://www.nfl.com/player/loganpaulsen/2507828/profile", "name": "Logan Paulsen"}, {"years_pro": 6, "status": "ACT", "first_name": "Tyler", "last_name": "Polumbus", "gsis_id": "00-0025826", "weight": 308, "position": "T", "playerid": "00-0025826", "profile_id": 836, "number": 74, "uniform_number": 74, "height": 80, "esb_id": "POL783118", "college": "Colorado", "birthdate": "4/10/1985", "full_name": "Tyler Polumbus", "team": "WAS", "player_id": "00-0025826", "gsis_name": "T.Polumbus", "profile_url": "http://www.nfl.com/player/tylerpolumbus/836/profile", "name": "Tyler Polumbus"}, {"years_pro": 0, "status": "ACT", "first_name": "Morgan", "last_name": "Moses", "gsis_id": "00-0031330", "weight": 318, "position": "OT", "playerid": "00-0031330", "profile_id": 2543489, "number": 76, "uniform_number": 76, "height": 78, "esb_id": "MOS280929", "college": "Virginia", "birthdate": "3/3/1991", "full_name": "Morgan Moses", "team": "WAS", "player_id": "00-0031330", "gsis_name": "M.Moses", "profile_url": "http://www.nfl.com/player/morganmoses/2543489/profile", "name": "Morgan Moses"}, {"years_pro": 4, "status": "RES", "first_name": "Chris", "last_name": "Neild", "gsis_id": "00-0028191", "weight": 328, "position": "NT", "playerid": "00-0028191", "profile_id": 2495319, "number": 95, "uniform_number": 95, "height": 74, "esb_id": "NEI522034", "college": "West Virginia", "birthdate": "12/1/1987", "full_name": "Chris Neild", "team": "WAS", "player_id": "00-0028191", "gsis_name": "C.Neild", "profile_url": "http://www.nfl.com/player/chrisneild/2495319/profile", "name": "Chris Neild"}, {"years_pro": 2, "status": "ACT", "first_name": "Jordan", "last_name": "Reed", "gsis_id": "00-0030472", "weight": 237, "position": "TE", "playerid": "00-0030472", "profile_id": 2540160, "number": 86, "uniform_number": 86, "height": 74, "esb_id": "REE302847", "college": "Florida", "birthdate": "7/3/1990", "full_name": "Jordan Reed", "team": "WAS", "player_id": "00-0030472", "gsis_name": "J.Reed", "profile_url": "http://www.nfl.com/player/jordanreed/2540160/profile", "name": "Jordan Reed"}, {"years_pro": 5, "status": "ACT", "first_name": "Clifton", "last_name": "Geathers", "gsis_id": "00-0027784", "weight": 325, "position": "DT", "playerid": "00-0027784", "profile_id": 496784, "number": 94, "uniform_number": 94, "height": 80, "esb_id": "GEA408541", "college": "South Carolina", "birthdate": "12/11/1987", "full_name": "Clifton Geathers", "team": "WAS", "player_id": "00-0027784", "gsis_name": "C.Geathers", "profile_url": "http://www.nfl.com/player/cliftongeathers/496784/profile", "name": "Clifton Geathers"}, {"years_pro": 9, "status": "PUP", "first_name": "Stephen", "last_name": "Bowen", "gsis_id": "00-0023954", "weight": 300, "position": "DE", "playerid": "00-0023954", "profile_id": 2506738, "number": 72, "uniform_number": 72, "height": 77, "esb_id": "BOW129829", "college": "Hofstra", "birthdate": "3/28/1984", "full_name": "Stephen Bowen", "team": "WAS", "player_id": "00-0023954", "gsis_name": "S.Bowen", "profile_url": "http://www.nfl.com/player/stephenbowen/2506738/profile", "name": "Stephen Bowen"}, {"years_pro": 0, "status": "ACT", "first_name": "Spencer", "last_name": "Long", "gsis_id": "00-0031047", "weight": 311, "position": "OG", "playerid": "00-0031047", "profile_id": 2550140, "number": 60, "uniform_number": 60, "height": 77, "esb_id": "LON548655", "college": "Nebraska", "birthdate": "11/8/1990", "full_name": "Spencer Long", "team": "WAS", "player_id": "00-0031047", "gsis_name": "", "profile_url": "http://www.nfl.com/player/spencerlong/2550140/profile", "name": "Spencer Long"}, {"years_pro": 4, "status": "PUP", "first_name": "Leonard", "last_name": "Hankerson", "gsis_id": "00-0028017", "weight": 211, "position": "WR", "playerid": "00-0028017", "profile_id": 2495158, "number": 85, "uniform_number": 85, "height": 74, "esb_id": "HAN169573", "college": "Miami (Fla.)", "birthdate": "1/30/1989", "full_name": "Leonard Hankerson", "team": "WAS", "player_id": "00-0028017", "gsis_name": "L.Hankerson", "profile_url": "http://www.nfl.com/player/leonardhankerson/2495158/profile", "name": "Leonard Hankerson"}, {"years_pro": 0, "status": "ACT", "first_name": "Silas", "last_name": "Redd", "gsis_id": "00-0031008", "weight": 200, "position": "RB", "playerid": "00-0031008", "profile_id": 2550529, "number": 32, "uniform_number": 32, "height": 70, "esb_id": "RED271501", "college": "USC", "birthdate": "3/1/1992", "full_name": "Silas Redd", "team": "WAS", "player_id": "00-0031008", "gsis_name": "S.Redd", "profile_url": "http://www.nfl.com/player/silasredd/2550529/profile", "name": "Silas Redd"}, {"years_pro": 1, "status": "ACT", "first_name": "Tress", "last_name": "Way", "gsis_id": "00-0030140", "weight": 215, "position": "P", "playerid": "00-0030140", "profile_id": 2541903, "number": 5, "uniform_number": 5, "height": 73, "esb_id": "WAY228645", "college": "Oklahoma", "birthdate": "4/18/1990", "full_name": "Tress Way", "team": "WAS", "player_id": "00-0030140", "gsis_name": "T.Way", "profile_url": "http://www.nfl.com/player/tressway/2541903/profile", "name": "Tress Way"}]
